<?xml version="1.0" encoding="utf-8"?>
<odoo>
        <!-- point_of_sale assets -->
        <template id="assets" name="cashbox assets">

            <link rel="stylesheet" href="/web/static/lib/fontawesome/css/font-awesome.css" />
            <link rel="stylesheet" type="text/less" href="/web/static/src/less/fonts.less" />
            
            <!-- Debería depender del pos y heredar esto? por ahora no estraemos de aquí mismo -->
            <!-- <link rel="stylesheet" href="/point_of_sale/static/src/css/pos.css" id="pos-stylesheet"/>
            <link rel="stylesheet" href="/point_of_sale/static/src/css/keyboard.css" /> -->
            <link rel="stylesheet" href="/cashbox/static/src/css/pos.css" id="pos-stylesheet"/>
            <link rel="stylesheet" href="/cashbox/static/src/css/keyboard.css" />

            <script type="text/javascript" src="/cashbox/static/lib/fastclick.js"></script>
            <script type="text/javascript" src="/cashbox/static/lib/waitfont.js"></script>
            <script type="text/javascript" src="/cashbox/static/src/js/main.js"></script>
            <script type="text/javascript" src="/cashbox/static/src/js/db.js"></script>
            <script type="text/javascript" src="/cashbox/static/src/js/models.js"></script>
            <script type="text/javascript" src="/cashbox/static/src/js/widget_base.js"></script>
            <script type="text/javascript" src="/cashbox/static/src/js/keyboard.js"></script>
            <script type="text/javascript" src="/cashbox/static/src/js/chrome.js"></script>
            <script type="text/javascript" src="/cashbox/static/src/js/devices.js"></script>
            <script type="text/javascript" src="/cashbox/static/src/js/gui.js"></script>
            <script type="text/javascript" src="/cashbox/static/src/js/popups.js"></script>
            <script type="text/javascript" src="/cashbox/static/src/js/screens.js"></script>
            <script type="text/javascript" src="/cashbox/static/src/js/tests.js"></script>
        </template>
</odoo>
